<?xml version="1.0" encoding="utf-8" ?>
<c2layout>
    <name>CENARIO2</name>
    <sid>365975140037540</sid>
    <event-sheet>CENARIO2</event-sheet>
    <size>
        <width>1000</width>
        <height>600</height>
    </size>
    <margins>
        <horizontal>1</horizontal>
        <vertical>1</vertical>
    </margins>
    <unbounded-scrolling>0</unbounded-scrolling>
    <layers>
        <layer name="BACKGROUND" sid="320412068688366">
            <initially-visible>1</initially-visible>
            <background-color>0,0,0</background-color>
            <transparent>0</transparent>
            <parallax>
                <x>1</x>
                <y>1</y>
            </parallax>
            <zoom-rate>1</zoom-rate>
            <opacity>1</opacity>
            <force-own-texture>0</force-own-texture>
            <global>0</global>
            <use-render-cells>0</use-render-cells>
            <blend-mode>0</blend-mode>
            <effect-fallback>0</effect-fallback>
            <instances>
                <instance type="background_one" uid="11">
                    <properties>
                        <initial-visibility>Visible</initial-visibility>
                        <hotspot>Top-left</hotspot>
                    </properties>
                    <blend-mode>0</blend-mode>
                    <effect-fallback>0</effect-fallback>
                    <world>
                        <x>0</x>
                        <y>15</y>
                        <z>0</z>
                        <width>1000</width>
                        <height>569</height>
                        <depth>0</depth>
                        <hotspotX>0</hotspotX>
                        <hotspotY>0</hotspotY>
                        <angle>0</angle>
                        <opacity>1</opacity>
                    </world>
                </instance>
            </instances>
            <effects />
        </layer>
        <layer name="CENARIO" sid="367832637988157">
            <initially-visible>1</initially-visible>
            <background-color>255,255,255</background-color>
            <transparent>1</transparent>
            <parallax>
                <x>1</x>
                <y>1</y>
            </parallax>
            <zoom-rate>1</zoom-rate>
            <opacity>1</opacity>
            <force-own-texture>0</force-own-texture>
            <global>0</global>
            <use-render-cells>0</use-render-cells>
            <blend-mode>0</blend-mode>
            <effect-fallback>0</effect-fallback>
            <instances>
                <instance type="sangue" uid="39">
                    <properties>
                        <initial-visibility>Visible</initial-visibility>
                        <initial-animation>Default</initial-animation>
                        <initial-frame>0</initial-frame>
                        <collisions>Enabled</collisions>
                    </properties>
                    <instance-variables>
                        <name>Default</name>
                        <isDragable>0</isDragable>
                        <isVisible>0</isVisible>
                        <canClick>0</canClick>
                        <toolbox>0</toolbox>
                        <killonuse>false</killonuse>
                        <canPick>false</canPick>
                    </instance-variables>
                    <blend-mode>0</blend-mode>
                    <effect-fallback>0</effect-fallback>
                    <world>
                        <x>624</x>
                        <y>368</y>
                        <z>0</z>
                        <width>495</width>
                        <height>324</height>
                        <depth>0</depth>
                        <hotspotX>0.50101012</hotspotX>
                        <hotspotY>0.5</hotspotY>
                        <angle>0</angle>
                        <opacity>1</opacity>
                    </world>
                </instance>
                <instance type="lampada_default" uid="47">
                    <properties>
                        <initial-visibility>Visible</initial-visibility>
                        <initial-animation>Default</initial-animation>
                        <initial-frame>0</initial-frame>
                        <collisions>Enabled</collisions>
                    </properties>
                    <blend-mode>0</blend-mode>
                    <effect-fallback>0</effect-fallback>
                    <world>
                        <x>500</x>
                        <y>133</y>
                        <z>0</z>
                        <width>52</width>
                        <height>187</height>
                        <depth>0</depth>
                        <hotspotX>0.5</hotspotX>
                        <hotspotY>0.502673805</hotspotY>
                        <angle>0</angle>
                        <opacity>1</opacity>
                    </world>
                </instance>
            </instances>
            <effects />
        </layer>
        <layer name="OBJETOS" sid="383211192835407">
            <initially-visible>1</initially-visible>
            <background-color>255,255,255</background-color>
            <transparent>1</transparent>
            <parallax>
                <x>1</x>
                <y>1</y>
            </parallax>
            <zoom-rate>1</zoom-rate>
            <opacity>1</opacity>
            <force-own-texture>0</force-own-texture>
            <global>0</global>
            <use-render-cells>0</use-render-cells>
            <blend-mode>0</blend-mode>
            <effect-fallback>0</effect-fallback>
            <instances>
                <instance type="bau" uid="34">
                    <properties>
                        <initial-visibility>Visible</initial-visibility>
                        <initial-animation>Default</initial-animation>
                        <initial-frame>0</initial-frame>
                        <collisions>Enabled</collisions>
                    </properties>
                    <instance-variables>
                        <name>Bau</name>
                        <isDragable>0</isDragable>
                        <isVisible>0</isVisible>
                        <canClick>0</canClick>
                        <toolbox>0</toolbox>
                        <killonuse>false</killonuse>
                        <canPick>true</canPick>
                        <isOpened>false</isOpened>
                    </instance-variables>
                    <blend-mode>0</blend-mode>
                    <effect-fallback>0</effect-fallback>
                    <world>
                        <x>798</x>
                        <y>500</y>
                        <z>0</z>
                        <width>252</width>
                        <height>121</height>
                        <depth>0</depth>
                        <hotspotX>0.5</hotspotX>
                        <hotspotY>0.504132211</hotspotY>
                        <angle>0</angle>
                        <opacity>1</opacity>
                    </world>
                </instance>
                <instance type="fundo_janela" uid="73">
                    <properties>
                        <initial-visibility>Visible</initial-visibility>
                        <initial-animation>Default</initial-animation>
                        <initial-frame>0</initial-frame>
                        <collisions>Enabled</collisions>
                    </properties>
                    <blend-mode>0</blend-mode>
                    <effect-fallback>0</effect-fallback>
                    <world>
                        <x>210</x>
                        <y>283.5</y>
                        <z>0</z>
                        <width>182</width>
                        <height>123</height>
                        <depth>0</depth>
                        <hotspotX>0.5</hotspotX>
                        <hotspotY>0.5</hotspotY>
                        <angle>0</angle>
                        <opacity>0.699999988</opacity>
                    </world>
                </instance>
                <instance type="fundo_janela_flash" uid="74">
                    <properties>
                        <initial-visibility>Visible</initial-visibility>
                        <initial-animation>Default</initial-animation>
                        <initial-frame>0</initial-frame>
                        <collisions>Enabled</collisions>
                    </properties>
                    <behavior-instances>
                        <behavior-instance type="Flash" />
                    </behavior-instances>
                    <blend-mode>0</blend-mode>
                    <effect-fallback>0</effect-fallback>
                    <world>
                        <x>210</x>
                        <y>283.5</y>
                        <z>0</z>
                        <width>182</width>
                        <height>123</height>
                        <depth>0</depth>
                        <hotspotX>0.5</hotspotX>
                        <hotspotY>0.5</hotspotY>
                        <angle>0</angle>
                        <opacity>1</opacity>
                    </world>
                </instance>
                <instance type="janela" uid="35">
                    <properties>
                        <initial-visibility>Visible</initial-visibility>
                        <initial-animation>Default</initial-animation>
                        <initial-frame>0</initial-frame>
                        <collisions>Enabled</collisions>
                    </properties>
                    <instance-variables>
                        <name>Janela</name>
                        <isDragable>0</isDragable>
                        <isVisible>0</isVisible>
                        <canClick>0</canClick>
                        <toolbox>0</toolbox>
                        <killonuse>false</killonuse>
                        <canPick>false</canPick>
                    </instance-variables>
                    <effect-instances>
                        <effect-instance type="Outline">
                            <parameters>
                                <blue>255</blue>
                                <green>255</green>
                                <just-outline>0</just-outline>
                                <red>255</red>
                                <width>2</width>
                            </parameters>
                        </effect-instance>
                    </effect-instances>
                    <blend-mode>0</blend-mode>
                    <effect-fallback>0</effect-fallback>
                    <world>
                        <x>215</x>
                        <y>281</y>
                        <z>0</z>
                        <width>252</width>
                        <height>267</height>
                        <depth>0</depth>
                        <hotspotX>0.5</hotspotX>
                        <hotspotY>0.501872659</hotspotY>
                        <angle>0</angle>
                        <opacity>1</opacity>
                    </world>
                </instance>
                <instance type="papelNomes" uid="36">
                    <properties>
                        <initial-visibility>Visible</initial-visibility>
                        <initial-animation>Default</initial-animation>
                        <initial-frame>0</initial-frame>
                        <collisions>Enabled</collisions>
                    </properties>
                    <instance-variables>
                        <name>Bloco de Notas 2</name>
                        <isDragable>0</isDragable>
                        <isVisible>0</isVisible>
                        <canClick>0</canClick>
                        <toolbox>0</toolbox>
                        <killonuse>false</killonuse>
                        <canPick>true</canPick>
                    </instance-variables>
                    <blend-mode>0</blend-mode>
                    <effect-fallback>0</effect-fallback>
                    <world>
                        <x>439</x>
                        <y>311</y>
                        <z>0</z>
                        <width>31</width>
                        <height>46</height>
                        <depth>0</depth>
                        <hotspotX>0.516129017</hotspotX>
                        <hotspotY>0.5</hotspotY>
                        <angle>0</angle>
                        <opacity>1</opacity>
                    </world>
                </instance>
                <instance type="papelDatas" uid="37">
                    <properties>
                        <initial-visibility>Visible</initial-visibility>
                        <initial-animation>Default</initial-animation>
                        <initial-frame>0</initial-frame>
                        <collisions>Enabled</collisions>
                    </properties>
                    <instance-variables>
                        <name>Bloco de Notas 1</name>
                        <isDragable>0</isDragable>
                        <isVisible>0</isVisible>
                        <canClick>0</canClick>
                        <toolbox>0</toolbox>
                        <killonuse>false</killonuse>
                        <canPick>false</canPick>
                    </instance-variables>
                    <blend-mode>0</blend-mode>
                    <effect-fallback>0</effect-fallback>
                    <world>
                        <x>380</x>
                        <y>274</y>
                        <z>0</z>
                        <width>36</width>
                        <height>56</height>
                        <depth>0</depth>
                        <hotspotX>0.5</hotspotX>
                        <hotspotY>0.5</hotspotY>
                        <angle>0</angle>
                        <opacity>1</opacity>
                    </world>
                </instance>
                <instance type="prateleira" uid="38">
                    <properties>
                        <initial-visibility>Visible</initial-visibility>
                        <initial-animation>Default</initial-animation>
                        <initial-frame>0</initial-frame>
                        <collisions>Enabled</collisions>
                    </properties>
                    <instance-variables>
                        <name>Prateleira Vazia</name>
                        <isDragable>0</isDragable>
                        <isVisible>0</isVisible>
                        <canClick>0</canClick>
                        <toolbox>1</toolbox>
                        <killonuse>false</killonuse>
                        <canPick>false</canPick>
                    </instance-variables>
                    <blend-mode>0</blend-mode>
                    <effect-fallback>0</effect-fallback>
                    <world>
                        <x>795</x>
                        <y>241</y>
                        <z>0</z>
                        <width>342</width>
                        <height>112</height>
                        <depth>0</depth>
                        <hotspotX>0.5</hotspotX>
                        <hotspotY>0.5</hotspotY>
                        <angle>0</angle>
                        <opacity>1</opacity>
                    </world>
                </instance>
                <instance type="sourc_hist" uid="80">
                    <properties>
                        <character-width>16</character-width>
                        <character-height>16</character-height>
                        <character-set>ABCDEFGHIJKLMNOPQRSTUVWXYZabcdefghijklmnopqrstuvwxyz0123456789.,;:?!-_~#&quot;&apos;&amp;()[]|`\/@°+=*$£€&lt;&gt;</character-set>
                        <text></text>
                        <scale>1</scale>
                        <initial-visibility>Visible</initial-visibility>
                        <horizontal-alignment>Left</horizontal-alignment>
                        <vertical-alignment>Top</vertical-alignment>
                        <hotspot>Top-left</hotspot>
                        <wrapping>Word</wrapping>
                        <character-spacing>0</character-spacing>
                        <line-height>0</line-height>
                    </properties>
                    <blend-mode>0</blend-mode>
                    <effect-fallback>0</effect-fallback>
                    <world>
                        <x>148</x>
                        <y>-499</y>
                        <z>0</z>
                        <width>164</width>
                        <height>146</height>
                        <depth>0</depth>
                        <hotspotX>0</hotspotX>
                        <hotspotY>0</hotspotY>
                        <angle>0</angle>
                        <opacity>1</opacity>
                    </world>
                </instance>
            </instances>
            <effects />
        </layer>
        <layer name="lampada" sid="433334643165556">
            <initially-visible>1</initially-visible>
            <background-color>255,255,255</background-color>
            <transparent>1</transparent>
            <parallax>
                <x>1</x>
                <y>1</y>
            </parallax>
            <zoom-rate>1</zoom-rate>
            <opacity>1</opacity>
            <force-own-texture>0</force-own-texture>
            <global>0</global>
            <use-render-cells>0</use-render-cells>
            <blend-mode>0</blend-mode>
            <effect-fallback>0</effect-fallback>
            <instances>
                <instance type="lamp_light" uid="27">
                    <properties>
                        <initial-visibility>Visible</initial-visibility>
                        <initial-animation>Default</initial-animation>
                        <initial-frame>0</initial-frame>
                        <collisions>Enabled</collisions>
                    </properties>
                    <behavior-instances>
                        <behavior-instance type="Flash" />
                    </behavior-instances>
                    <blend-mode>0</blend-mode>
                    <effect-fallback>0</effect-fallback>
                    <world>
                        <x>500</x>
                        <y>217</y>
                        <z>0</z>
                        <width>20.56036377</width>
                        <height>15.519943237</height>
                        <depth>0</depth>
                        <hotspotX>0.5</hotspotX>
                        <hotspotY>0.449999988</hotspotY>
                        <angle>0</angle>
                        <opacity>1</opacity>
                    </world>
                </instance>
            </instances>
            <effects />
        </layer>
        <layer name="dark" sid="919593274914503">
            <initially-visible>1</initially-visible>
            <background-color>0,0,0</background-color>
            <transparent>0</transparent>
            <parallax>
                <x>1</x>
                <y>1</y>
            </parallax>
            <zoom-rate>1</zoom-rate>
            <opacity>1</opacity>
            <force-own-texture>0</force-own-texture>
            <global>0</global>
            <use-render-cells>0</use-render-cells>
            <blend-mode>0</blend-mode>
            <effect-fallback>0</effect-fallback>
            <instances>
                <instance type="darklight_lampada" uid="26">
                    <properties>
                        <initial-visibility>Visible</initial-visibility>
                        <initial-animation>Default</initial-animation>
                        <initial-frame>0</initial-frame>
                        <collisions>Enabled</collisions>
                    </properties>
                    <instance-variables>
                        <fullLight>0</fullLight>
                    </instance-variables>
                    <behavior-instances>
                        <behavior-instance type="Flash" />
                    </behavior-instances>
                    <blend-mode>0</blend-mode>
                    <effect-fallback>0</effect-fallback>
                    <world>
                        <x>500</x>
                        <y>218</y>
                        <z>0</z>
                        <width>600</width>
                        <height>600</height>
                        <depth>0</depth>
                        <hotspotX>0.5</hotspotX>
                        <hotspotY>0.5</hotspotY>
                        <angle>0</angle>
                        <opacity>1</opacity>
                    </world>
                </instance>
                <instance type="ib_nextPage" uid="122">
                    <properties>
                        <initial-visibility>Visible</initial-visibility>
                        <initial-animation>Default</initial-animation>
                        <initial-frame>0</initial-frame>
                        <collisions>Enabled</collisions>
                    </properties>
                    <behavior-instances>
                        <behavior-instance type="Pin" />
                    </behavior-instances>
                    <blend-mode>0</blend-mode>
                    <effect-fallback>0</effect-fallback>
                    <world>
                        <x>667.666625977</x>
                        <y>-29.666664124</y>
                        <z>0</z>
                        <width>56</width>
                        <height>47</height>
                        <depth>0</depth>
                        <hotspotX>0.5</hotspotX>
                        <hotspotY>0.510638297</hotspotY>
                        <angle>0</angle>
                        <opacity>1</opacity>
                    </world>
                </instance>
            </instances>
            <effects>
                <effect-type name="Multiply">
                    <effect id="multiply" />
                    <effect-instance type="Multiply" />
                </effect-type>
            </effects>
        </layer>
        <layer name="interacao" sid="279759341413547">
            <initially-visible>1</initially-visible>
            <background-color>255,255,255</background-color>
            <transparent>1</transparent>
            <parallax>
                <x>1</x>
                <y>1</y>
            </parallax>
            <zoom-rate>1</zoom-rate>
            <opacity>1</opacity>
            <force-own-texture>0</force-own-texture>
            <global>0</global>
            <use-render-cells>0</use-render-cells>
            <blend-mode>0</blend-mode>
            <effect-fallback>0</effect-fallback>
            <instances>
                <instance type="blackdrop" uid="67">
                    <properties>
                        <initial-visibility>Visible</initial-visibility>
                        <initial-animation>Default</initial-animation>
                        <initial-frame>0</initial-frame>
                        <collisions>Enabled</collisions>
                    </properties>
                    <blend-mode>0</blend-mode>
                    <effect-fallback>0</effect-fallback>
                    <world>
                        <x>-84</x>
                        <y>18</y>
                        <z>0</z>
                        <width>32</width>
                        <height>32</height>
                        <depth>0</depth>
                        <hotspotX>0.5</hotspotX>
                        <hotspotY>0.5</hotspotY>
                        <angle>0</angle>
                        <opacity>0.600000024</opacity>
                    </world>
                </instance>
                <instance type="fundo_janela_flash_all" uid="75">
                    <properties>
                        <initial-visibility>Visible</initial-visibility>
                        <initial-animation>Default</initial-animation>
                        <initial-frame>0</initial-frame>
                        <collisions>Enabled</collisions>
                    </properties>
                    <behavior-instances>
                        <behavior-instance type="Flash" />
                    </behavior-instances>
                    <blend-mode>0</blend-mode>
                    <effect-fallback>0</effect-fallback>
                    <world>
                        <x>-343</x>
                        <y>-217</y>
                        <z>0</z>
                        <width>172</width>
                        <height>108</height>
                        <depth>0</depth>
                        <hotspotX>0.5</hotspotX>
                        <hotspotY>0.5</hotspotY>
                        <angle>0</angle>
                        <opacity>1</opacity>
                    </world>
                </instance>
                <instance type="fundo_janela_flash_white" uid="76">
                    <properties>
                        <initial-visibility>Visible</initial-visibility>
                        <initial-animation>Default</initial-animation>
                        <initial-frame>0</initial-frame>
                        <collisions>Enabled</collisions>
                    </properties>
                    <blend-mode>0</blend-mode>
                    <effect-fallback>0</effect-fallback>
                    <world>
                        <x>18</x>
                        <y>-273</y>
                        <z>0</z>
                        <width>213</width>
                        <height>115</height>
                        <depth>0</depth>
                        <hotspotX>0.5</hotspotX>
                        <hotspotY>0.5</hotspotY>
                        <angle>0</angle>
                        <opacity>1</opacity>
                    </world>
                </instance>
                <instance type="LEFTARROW" uid="4">
                    <properties>
                        <initial-visibility>Visible</initial-visibility>
                        <initial-animation>&quot;on&quot;</initial-animation>
                        <initial-frame>0</initial-frame>
                        <collisions>Enabled</collisions>
                    </properties>
                    <blend-mode>0</blend-mode>
                    <effect-fallback>0</effect-fallback>
                    <world>
                        <x>50</x>
                        <y>300</y>
                        <z>0</z>
                        <width>63</width>
                        <height>63</height>
                        <depth>0</depth>
                        <hotspotX>0.507936537</hotspotX>
                        <hotspotY>0.507936537</hotspotY>
                        <angle>0</angle>
                        <opacity>1</opacity>
                    </world>
                </instance>
                <instance type="RIGHTARROW" uid="23">
                    <properties>
                        <initial-visibility>Visible</initial-visibility>
                        <initial-animation>&quot;on&quot;</initial-animation>
                        <initial-frame>0</initial-frame>
                        <collisions>Enabled</collisions>
                    </properties>
                    <blend-mode>0</blend-mode>
                    <effect-fallback>0</effect-fallback>
                    <world>
                        <x>950</x>
                        <y>300</y>
                        <z>0</z>
                        <width>63</width>
                        <height>63</height>
                        <depth>0</depth>
                        <hotspotX>0.507936537</hotspotX>
                        <hotspotY>0.507936537</hotspotY>
                        <angle>0</angle>
                        <opacity>1</opacity>
                    </world>
                </instance>
                <instance type="GameMessage" uid="58">
                    <properties>
                        <character-width>16</character-width>
                        <character-height>16</character-height>
                        <character-set>ABCDEFGHIJKLMNOPQRSTUVWXYZabcdefghijklmnopqrstuvwxyz0123456789.,;:?!-_~#&quot;&apos;&amp;()[]|`\/@°+=*$£€&lt;&gt;</character-set>
                        <text>Default</text>
                        <scale>1</scale>
                        <initial-visibility>Visible</initial-visibility>
                        <horizontal-alignment>Center</horizontal-alignment>
                        <vertical-alignment>Top</vertical-alignment>
                        <hotspot>Center</hotspot>
                        <wrapping>Word</wrapping>
                        <character-spacing>0</character-spacing>
                        <line-height>0</line-height>
                    </properties>
                    <behavior-instances>
                        <behavior-instance type="Fade">
                            <properties>
                                <active-at-start>No</active-at-start>
                                <fade-in-time>0</fade-in-time>
                                <wait-time>0</wait-time>
                                <fade-out-time>1</fade-out-time>
                                <destroy>No</destroy>
                            </properties>
                        </behavior-instance>
                    </behavior-instances>
                    <blend-mode>0</blend-mode>
                    <effect-fallback>0</effect-fallback>
                    <world>
                        <x>960</x>
                        <y>855</y>
                        <z>0</z>
                        <width>339</width>
                        <height>30</height>
                        <depth>0</depth>
                        <hotspotX>0.5</hotspotX>
                        <hotspotY>0.5</hotspotY>
                        <angle>0</angle>
                        <opacity>1</opacity>
                    </world>
                </instance>
                <instance type="dialog" uid="77">
                    <properties>
                        <initial-visibility>Visible</initial-visibility>
                        <initial-animation>Default</initial-animation>
                        <initial-frame>0</initial-frame>
                        <collisions>Enabled</collisions>
                    </properties>
                    <instance-variables>
                        <show>0</show>
                    </instance-variables>
                    <behavior-instances>
                        <behavior-instance type="Sine">
                            <properties>
                                <active-on-start>No</active-on-start>
                                <movement>Vertical</movement>
                                <wave>Sine</wave>
                                <period>2</period>
                                <period-random>0</period-random>
                                <period-offset>0</period-offset>
                                <period-offset-random>0</period-offset-random>
                                <magnitude>150</magnitude>
                                <magnitude-random>0</magnitude-random>
                            </properties>
                        </behavior-instance>
                        <behavior-instance type="LiteTween">
                            <properties>
                                <active-on-start>No</active-on-start>
                                <tweened-property>Position</tweened-property>
                                <function>EaseInElastic</function>
                                <target>500,500</target>
                                <target-mode>Absolute</target-mode>
                                <duration>2.5</duration>
                                <enforce-mode>Enforce</enforce-mode>
                            </properties>
                        </behavior-instance>
                    </behavior-instances>
                    <blend-mode>0</blend-mode>
                    <effect-fallback>0</effect-fallback>
                    <world>
                        <x>504</x>
                        <y>681</y>
                        <z>0</z>
                        <width>742</width>
                        <height>122</height>
                        <depth>0</depth>
                        <hotspotX>0.5</hotspotX>
                        <hotspotY>0.459016383</hotspotY>
                        <angle>0</angle>
                        <opacity>1</opacity>
                    </world>
                </instance>
                <instance type="NewDialogText" uid="79">
                    <properties>
                        <character-width>22</character-width>
                        <character-height>22</character-height>
                        <character-set>ABCDEFGHIJKLMNOPQRSTUVWXYZabcdefghijklmnopqrstuvwxyz0123456789.,;:?!-_~#&quot;&apos;&amp;()[]|`\/@°+=*$£€&lt;&gt;%ÁáÂâÀàÅåÃãÄäÆæÉéÊêÈèËëÍíÎîÌìÏïÓóÔôÒòÕõÖöÚúÛûùÙÜüÇçÑñÝý¿</character-set>
                        <text>....</text>
                        <scale>1</scale>
                        <initial-visibility>Visible</initial-visibility>
                        <horizontal-alignment>Left</horizontal-alignment>
                        <vertical-alignment>Top</vertical-alignment>
                        <hotspot>Top-left</hotspot>
                        <wrapping>Word</wrapping>
                        <character-spacing>0</character-spacing>
                        <line-height>0</line-height>
                        <char-width-json>{&quot;&quot;c2array&quot;&quot;:true,&quot;&quot;size&quot;&quot;:[2,12,1],&quot;&quot;data&quot;&quot;:[[[6],[4],[6],[7],[8],[9],[10],[11],[12],[13],[14],[20]],[[&quot;&quot; &quot;&quot;],[&quot;&quot;|&quot;&quot;],[&quot;&quot;.,;:&apos;&quot;&quot;],[&quot;&quot;()&quot;&quot;],[&quot;&quot;`°&quot;&quot;],[&quot;&quot;[]&quot;&quot;],[&quot;&quot;!-#\&quot;&quot;£€&lt;&gt;&quot;&quot;],[&quot;&quot;ì&quot;&quot;],[&quot;&quot;ITYity1~+%ÍíÎîÌÏïÝý&quot;&quot;],[&quot;&quot;ABCDEFGHJKLMNOPQRSUVWXZabcdfghjklmnopqrsuvwxz023456789?_&amp;\\/@=*$ÁáÂâÀàÅåÃãÄäÉéÊêÈèËëóÔôòÕõÖöÚúÛûùÙÜüçÑñ¿&quot;&quot;],[&quot;&quot;eÓÒÇ&quot;&quot;],[&quot;&quot;Ææ&quot;&quot;]]]}</char-width-json>
                        <space-char-width>-1</space-char-width>
                    </properties>
                    <instance-variables>
                        <writing>0</writing>
                    </instance-variables>
                    <blend-mode>0</blend-mode>
                    <effect-fallback>0</effect-fallback>
                    <world>
                        <x>279</x>
                        <y>648</y>
                        <z>0</z>
                        <width>577</width>
                        <height>80</height>
                        <depth>0</depth>
                        <hotspotX>0</hotspotX>
                        <hotspotY>0</hotspotY>
                        <angle>0</angle>
                        <opacity>1</opacity>
                    </world>
                </instance>
                <instance type="personagem_1" uid="78">
                    <properties>
                        <initial-visibility>Visible</initial-visibility>
                        <initial-animation>animation</initial-animation>
                        <initial-frame>0</initial-frame>
                        <collisions>Enabled</collisions>
                    </properties>
                    <blend-mode>0</blend-mode>
                    <effect-fallback>0</effect-fallback>
                    <world>
                        <x>-33</x>
                        <y>791</y>
                        <z>0</z>
                        <width>50.249378204</width>
                        <height>100.498756409</height>
                        <depth>0</depth>
                        <hotspotX>0.5</hotspotX>
                        <hotspotY>0.5</hotspotY>
                        <angle>0</angle>
                        <opacity>1</opacity>
                    </world>
                </instance>
                <instance type="bloco_datas" uid="65">
                    <properties>
                        <initial-visibility>Visible</initial-visibility>
                        <initial-animation>Default</initial-animation>
                        <initial-frame>0</initial-frame>
                        <collisions>Enabled</collisions>
                    </properties>
                    <instance-variables>
                        <isOpen>false</isOpen>
                    </instance-variables>
                    <behavior-instances>
                        <behavior-instance type="Sine">
                            <properties>
                                <active-on-start>No</active-on-start>
                                <movement>Vertical</movement>
                                <wave>Sine</wave>
                                <period>4</period>
                                <period-random>0</period-random>
                                <period-offset>0</period-offset>
                                <period-offset-random>0</period-offset-random>
                                <magnitude>20</magnitude>
                                <magnitude-random>2</magnitude-random>
                            </properties>
                        </behavior-instance>
                    </behavior-instances>
                    <blend-mode>0</blend-mode>
                    <effect-fallback>0</effect-fallback>
                    <world>
                        <x>-126</x>
                        <y>261</y>
                        <z>0</z>
                        <width>230</width>
                        <height>256</height>
                        <depth>0</depth>
                        <hotspotX>0.5</hotspotX>
                        <hotspotY>0.5</hotspotY>
                        <angle>0</angle>
                        <opacity>1</opacity>
                    </world>
                </instance>
                <instance type="bloco_nomes" uid="71">
                    <properties>
                        <initial-visibility>Visible</initial-visibility>
                        <initial-animation>Default</initial-animation>
                        <initial-frame>0</initial-frame>
                        <collisions>Enabled</collisions>
                    </properties>
                    <instance-variables>
                        <isOpen>false</isOpen>
                    </instance-variables>
                    <behavior-instances>
                        <behavior-instance type="Sine">
                            <properties>
                                <active-on-start>No</active-on-start>
                                <movement>Vertical</movement>
                                <wave>Sine</wave>
                                <period>4</period>
                                <period-random>0</period-random>
                                <period-offset>0</period-offset>
                                <period-offset-random>0</period-offset-random>
                                <magnitude>20</magnitude>
                                <magnitude-random>4</magnitude-random>
                            </properties>
                        </behavior-instance>
                    </behavior-instances>
                    <blend-mode>0</blend-mode>
                    <effect-fallback>0</effect-fallback>
                    <world>
                        <x>-231</x>
                        <y>519</y>
                        <z>0</z>
                        <width>230</width>
                        <height>256</height>
                        <depth>0</depth>
                        <hotspotX>0.5</hotspotX>
                        <hotspotY>0.5</hotspotY>
                        <angle>0</angle>
                        <opacity>1</opacity>
                    </world>
                </instance>
                <instance type="notepadDatas" uid="124">
                    <properties>
                        <character-width>16</character-width>
                        <character-height>16</character-height>
                        <character-set>ABCDEFGHIJKLMNOPQRSTUVWXYZabcdefghijklmnopqrstuvwxyz0123456789.,;:?!-_~#&quot;&apos;&amp;()[]|`\/@°+=*$£€&lt;&gt;</character-set>
                        <text>1992 \n 1212</text>
                        <scale>1</scale>
                        <initial-visibility>Visible</initial-visibility>
                        <horizontal-alignment>Left</horizontal-alignment>
                        <vertical-alignment>Top</vertical-alignment>
                        <hotspot>Top-left</hotspot>
                        <wrapping>Word</wrapping>
                        <character-spacing>0</character-spacing>
                        <line-height>0</line-height>
                        <char-width-json></char-width-json>
                        <space-char-width>-1</space-char-width>
                    </properties>
                    <behavior-instances>
                        <behavior-instance type="Pin" />
                    </behavior-instances>
                    <blend-mode>0</blend-mode>
                    <effect-fallback>0</effect-fallback>
                    <world>
                        <x>-223</x>
                        <y>175</y>
                        <z>0</z>
                        <width>198</width>
                        <height>196</height>
                        <depth>0</depth>
                        <hotspotX>0</hotspotX>
                        <hotspotY>0</hotspotY>
                        <angle>0</angle>
                        <opacity>1</opacity>
                    </world>
                </instance>
                <instance type="dbTextItem" uid="212">
                    <properties>
                        <text>Text</text>
                        <initial-visibility>Visible</initial-visibility>
                        <font>VCR OSD Mono,-16,400,0</font>
                        <color>0,255,0</color>
                        <horizontal-alignment>Center</horizontal-alignment>
                        <vertical-alignment>Center</vertical-alignment>
                        <hotspot>Center</hotspot>
                        <wrapping>Word</wrapping>
                        <line-height>0</line-height>
                    </properties>
                    <blend-mode>0</blend-mode>
                    <effect-fallback>0</effect-fallback>
                    <world>
                        <x>1325</x>
                        <y>688</y>
                        <z>0</z>
                        <width>200</width>
                        <height>30</height>
                        <depth>0</depth>
                        <hotspotX>0.5</hotspotX>
                        <hotspotY>0.5</hotspotY>
                        <angle>0</angle>
                        <opacity>1</opacity>
                    </world>
                </instance>
            </instances>
            <effects />
        </layer>
        <layer name="gui" sid="132021973333029">
            <initially-visible>1</initially-visible>
            <background-color>255,255,255</background-color>
            <transparent>1</transparent>
            <parallax>
                <x>1</x>
                <y>1</y>
            </parallax>
            <zoom-rate>1</zoom-rate>
            <opacity>1</opacity>
            <force-own-texture>0</force-own-texture>
            <global>0</global>
            <use-render-cells>0</use-render-cells>
            <blend-mode>0</blend-mode>
            <effect-fallback>0</effect-fallback>
            <instances>
                <instance type="iventory_bar" uid="153">
                    <properties>
                        <initial-visibility>Visible</initial-visibility>
                        <initial-animation>Default</initial-animation>
                        <initial-frame>0</initial-frame>
                        <collisions>Enabled</collisions>
                    </properties>
                    <behavior-instances>
                        <behavior-instance type="LiteTween">
                            <properties>
                                <active-on-start>No</active-on-start>
                                <tweened-property>Vertical</tweened-property>
                                <function>EaseOutBounce</function>
                                <target>100,100</target>
                                <target-mode>Absolute</target-mode>
                                <duration>1.5</duration>
                                <enforce-mode>Enforce</enforce-mode>
                            </properties>
                        </behavior-instance>
                    </behavior-instances>
                    <blend-mode>0</blend-mode>
                    <effect-fallback>0</effect-fallback>
                    <world>
                        <x>492</x>
                        <y>-48</y>
                        <z>0</z>
                        <width>530</width>
                        <height>95</height>
                        <depth>0</depth>
                        <hotspotX>0.5</hotspotX>
                        <hotspotY>0.50526315</hotspotY>
                        <angle>0</angle>
                        <opacity>1</opacity>
                    </world>
                </instance>
                <instance type="ib_previusPage" uid="155">
                    <properties>
                        <initial-visibility>Visible</initial-visibility>
                        <initial-animation>Default</initial-animation>
                        <initial-frame>0</initial-frame>
                        <collisions>Enabled</collisions>
                    </properties>
                    <behavior-instances>
                        <behavior-instance type="Pin" />
                    </behavior-instances>
                    <blend-mode>0</blend-mode>
                    <effect-fallback>0</effect-fallback>
                    <world>
                        <x>186</x>
                        <y>-45</y>
                        <z>0</z>
                        <width>56</width>
                        <height>47</height>
                        <depth>0</depth>
                        <hotspotX>0.5</hotspotX>
                        <hotspotY>0.510638297</hotspotY>
                        <angle>0</angle>
                        <opacity>1</opacity>
                    </world>
                </instance>
                <instance type="ib_nextPage" uid="154">
                    <properties>
                        <initial-visibility>Visible</initial-visibility>
                        <initial-animation>Default</initial-animation>
                        <initial-frame>0</initial-frame>
                        <collisions>Enabled</collisions>
                    </properties>
                    <behavior-instances>
                        <behavior-instance type="Pin" />
                    </behavior-instances>
                    <blend-mode>0</blend-mode>
                    <effect-fallback>0</effect-fallback>
                    <world>
                        <x>799</x>
                        <y>-46</y>
                        <z>0</z>
                        <width>56</width>
                        <height>47</height>
                        <depth>0</depth>
                        <hotspotX>0.5</hotspotX>
                        <hotspotY>0.510638297</hotspotY>
                        <angle>0</angle>
                        <opacity>1</opacity>
                    </world>
                </instance>
                <instance type="slote" uid="152">
                    <properties>
                        <initial-visibility>Visible</initial-visibility>
                        <initial-animation>Default</initial-animation>
                        <initial-frame>0</initial-frame>
                        <collisions>Enabled</collisions>
                    </properties>
                    <instance-variables>
                        <config>false</config>
                        <slote_id></slote_id>
                    </instance-variables>
                    <behavior-instances>
                        <behavior-instance type="Pin" />
                    </behavior-instances>
                    <blend-mode>0</blend-mode>
                    <effect-fallback>0</effect-fallback>
                    <world>
                        <x>276</x>
                        <y>-51</y>
                        <z>0</z>
                        <width>71</width>
                        <height>71</height>
                        <depth>0</depth>
                        <hotspotX>0.507042229</hotspotX>
                        <hotspotY>0.507042229</hotspotY>
                        <angle>0</angle>
                        <opacity>1</opacity>
                    </world>
                </instance>
            </instances>
            <effects />
        </layer>
        <layer name="modal" sid="423915619553453">
            <initially-visible>1</initially-visible>
            <background-color>255,255,255</background-color>
            <transparent>1</transparent>
            <parallax>
                <x>1</x>
                <y>1</y>
            </parallax>
            <zoom-rate>1</zoom-rate>
            <opacity>1</opacity>
            <force-own-texture>0</force-own-texture>
            <global>0</global>
            <use-render-cells>0</use-render-cells>
            <blend-mode>0</blend-mode>
            <effect-fallback>0</effect-fallback>
            <instances>
                <instance type="bau_bg_modal" uid="140">
                    <properties>
                        <initial-visibility>Visible</initial-visibility>
                        <initial-animation>Default</initial-animation>
                        <initial-frame>0</initial-frame>
                        <collisions>Enabled</collisions>
                    </properties>
                    <instance-variables>
                        <isOpen>false</isOpen>
                        <BAU_ID>0</BAU_ID>
                    </instance-variables>
                    <blend-mode>0</blend-mode>
                    <effect-fallback>0</effect-fallback>
                    <world>
                        <x>1462</x>
                        <y>6</y>
                        <z>0</z>
                        <width>838</width>
                        <height>501</height>
                        <depth>0</depth>
                        <hotspotX>0.5</hotspotX>
                        <hotspotY>0.50099802</hotspotY>
                        <angle>0</angle>
                        <opacity>1</opacity>
                    </world>
                </instance>
                <instance type="bau_skin_modal" uid="141">
                    <properties>
                        <initial-visibility>Visible</initial-visibility>
                        <initial-animation>Default</initial-animation>
                        <initial-frame>0</initial-frame>
                        <collisions>Enabled</collisions>
                    </properties>
                    <instance-variables>
                        <isOpen>false</isOpen>
                        <BAU_ID>0</BAU_ID>
                    </instance-variables>
                    <blend-mode>0</blend-mode>
                    <effect-fallback>0</effect-fallback>
                    <world>
                        <x>1473</x>
                        <y>10</y>
                        <z>0</z>
                        <width>788</width>
                        <height>439</height>
                        <depth>0</depth>
                        <hotspotX>0.5</hotspotX>
                        <hotspotY>0.501138926</hotspotY>
                        <angle>0</angle>
                        <opacity>1</opacity>
                    </world>
                </instance>
                <instance type="bau_spr_password" uid="142">
                    <properties>
                        <initial-visibility>Visible</initial-visibility>
                        <initial-animation>Default</initial-animation>
                        <initial-frame>0</initial-frame>
                        <collisions>Enabled</collisions>
                    </properties>
                    <instance-variables>
                        <isOpen>false</isOpen>
                        <BAU_ID>0</BAU_ID>
                    </instance-variables>
                    <blend-mode>0</blend-mode>
                    <effect-fallback>0</effect-fallback>
                    <world>
                        <x>1475</x>
                        <y>-177</y>
                        <z>0</z>
                        <width>339</width>
                        <height>33</height>
                        <depth>0</depth>
                        <hotspotX>0.501474917</hotspotX>
                        <hotspotY>0.515151501</hotspotY>
                        <angle>0</angle>
                        <opacity>1</opacity>
                    </world>
                </instance>
                <instance type="close_bau_modal" uid="143">
                    <properties>
                        <initial-visibility>Visible</initial-visibility>
                        <initial-animation>Default</initial-animation>
                        <initial-frame>0</initial-frame>
                        <collisions>Enabled</collisions>
                    </properties>
                    <instance-variables>
                        <isOpen>false</isOpen>
                        <BAU_ID>0</BAU_ID>
                    </instance-variables>
                    <blend-mode>0</blend-mode>
                    <effect-fallback>0</effect-fallback>
                    <world>
                        <x>1863</x>
                        <y>-227</y>
                        <z>0</z>
                        <width>44</width>
                        <height>44</height>
                        <depth>0</depth>
                        <hotspotX>0.5</hotspotX>
                        <hotspotY>0.5</hotspotY>
                        <angle>0</angle>
                        <opacity>1</opacity>
                    </world>
                </instance>
                <instance type="slote_senha_modal" uid="144">
                    <properties>
                        <initial-visibility>Visible</initial-visibility>
                        <initial-animation>Default</initial-animation>
                        <initial-frame>0</initial-frame>
                        <collisions>Enabled</collisions>
                    </properties>
                    <instance-variables>
                        <isOpen>false</isOpen>
                        <BAU_ID>0</BAU_ID>
                    </instance-variables>
                    <blend-mode>0</blend-mode>
                    <effect-fallback>0</effect-fallback>
                    <world>
                        <x>772</x>
                        <y>-150</y>
                        <z>0</z>
                        <width>79</width>
                        <height>79</height>
                        <depth>0</depth>
                        <hotspotX>0.506329119</hotspotX>
                        <hotspotY>0.506329119</hotspotY>
                        <angle>0</angle>
                        <opacity>1</opacity>
                    </world>
                </instance>
                <instance type="tb_p1" uid="145">
                    <properties>
                        <text></text>
                        <placeholder></placeholder>
                        <tooltip></tooltip>
                        <initial-visibility>Visible</initial-visibility>
                        <enabled>Yes</enabled>
                        <read-only>No</read-only>
                        <spell-check>No</spell-check>
                        <type>Text</type>
                        <auto-font-size>No</auto-font-size>
                        <id-optional>p1box</id-optional>
                        <maxlength>1</maxlength>
                    </properties>
                    <blend-mode>0</blend-mode>
                    <effect-fallback>0</effect-fallback>
                    <world>
                        <x>309</x>
                        <y>-205</y>
                        <z>0</z>
                        <width>50</width>
                        <height>50</height>
                        <depth>0</depth>
                        <hotspotX>0</hotspotX>
                        <hotspotY>0</hotspotY>
                    </world>
                </instance>
                <instance type="tb_p2" uid="146">
                    <properties>
                        <text></text>
                        <placeholder></placeholder>
                        <tooltip></tooltip>
                        <initial-visibility>Visible</initial-visibility>
                        <enabled>Yes</enabled>
                        <read-only>No</read-only>
                        <spell-check>No</spell-check>
                        <type>Text</type>
                        <auto-font-size>No</auto-font-size>
                        <id-optional>p2box</id-optional>
                        <maxlength>1</maxlength>
                    </properties>
                    <blend-mode>0</blend-mode>
                    <effect-fallback>0</effect-fallback>
                    <world>
                        <x>409</x>
                        <y>-205</y>
                        <z>0</z>
                        <width>50</width>
                        <height>50</height>
                        <depth>0</depth>
                        <hotspotX>0</hotspotX>
                        <hotspotY>0</hotspotY>
                    </world>
                </instance>
                <instance type="tb_p3" uid="147">
                    <properties>
                        <text></text>
                        <placeholder></placeholder>
                        <tooltip></tooltip>
                        <initial-visibility>Visible</initial-visibility>
                        <enabled>Yes</enabled>
                        <read-only>No</read-only>
                        <spell-check>No</spell-check>
                        <type>Text</type>
                        <auto-font-size>No</auto-font-size>
                        <id-optional>p3box</id-optional>
                        <maxlength>1</maxlength>
                    </properties>
                    <blend-mode>0</blend-mode>
                    <effect-fallback>0</effect-fallback>
                    <world>
                        <x>509</x>
                        <y>-205</y>
                        <z>0</z>
                        <width>50</width>
                        <height>50</height>
                        <depth>0</depth>
                        <hotspotX>0</hotspotX>
                        <hotspotY>0</hotspotY>
                    </world>
                </instance>
                <instance type="tb_p4" uid="148">
                    <properties>
                        <text></text>
                        <placeholder></placeholder>
                        <tooltip></tooltip>
                        <initial-visibility>Visible</initial-visibility>
                        <enabled>Yes</enabled>
                        <read-only>No</read-only>
                        <spell-check>No</spell-check>
                        <type>Text</type>
                        <auto-font-size>No</auto-font-size>
                        <id-optional>p4box</id-optional>
                        <maxlength>1</maxlength>
                    </properties>
                    <blend-mode>0</blend-mode>
                    <effect-fallback>0</effect-fallback>
                    <world>
                        <x>609</x>
                        <y>-205</y>
                        <z>0</z>
                        <width>50</width>
                        <height>50</height>
                        <depth>0</depth>
                        <hotspotX>0</hotspotX>
                        <hotspotY>0</hotspotY>
                    </world>
                </instance>
                <instance type="dbText" uid="149">
                    <properties>
                        <text>Text</text>
                        <initial-visibility>Visible</initial-visibility>
                        <font>VCR OSD Mono,-16,400,0</font>
                        <color>0,255,51</color>
                        <horizontal-alignment>Center</horizontal-alignment>
                        <vertical-alignment>Center</vertical-alignment>
                        <hotspot>Center</hotspot>
                        <wrapping>Word</wrapping>
                        <line-height>0</line-height>
                    </properties>
                    <blend-mode>0</blend-mode>
                    <effect-fallback>0</effect-fallback>
                    <world>
                        <x>1210</x>
                        <y>503</y>
                        <z>0</z>
                        <width>503</width>
                        <height>30</height>
                        <depth>0</depth>
                        <hotspotX>0.5</hotspotX>
                        <hotspotY>0.5</hotspotY>
                        <angle>0</angle>
                        <opacity>1</opacity>
                    </world>
                </instance>
                <instance type="martelo_obj" uid="150">
                    <properties>
                        <initial-visibility>Visible</initial-visibility>
                        <initial-animation>Default</initial-animation>
                        <initial-frame>0</initial-frame>
                        <collisions>Enabled</collisions>
                    </properties>
                    <instance-variables>
                        <name>Banquinho</name>
                        <isDragable>0</isDragable>
                        <isVisible>0</isVisible>
                        <canClick>0</canClick>
                        <toolbox>0</toolbox>
                        <killonuse>false</killonuse>
                        <canPick>true</canPick>
                    </instance-variables>
                    <behavior-instances>
                        <behavior-instance type="Sine">
                            <properties>
                                <active-on-start>Yes</active-on-start>
                                <movement>Vertical</movement>
                                <wave>Sine</wave>
                                <period>4</period>
                                <period-random>0</period-random>
                                <period-offset>0</period-offset>
                                <period-offset-random>0</period-offset-random>
                                <magnitude>30</magnitude>
                                <magnitude-random>0</magnitude-random>
                            </properties>
                        </behavior-instance>
                    </behavior-instances>
                    <effect-instances>
                        <effect-instance type="Outline">
                            <parameters>
                                <blue>255</blue>
                                <green>255</green>
                                <just-outline>0</just-outline>
                                <red>255</red>
                                <width>3</width>
                            </parameters>
                        </effect-instance>
                    </effect-instances>
                    <blend-mode>0</blend-mode>
                    <effect-fallback>0</effect-fallback>
                    <world>
                        <x>985</x>
                        <y>812</y>
                        <z>0</z>
                        <width>107.224998474</width>
                        <height>178.708328247</height>
                        <depth>0</depth>
                        <hotspotX>0.5</hotspotX>
                        <hotspotY>0.5</hotspotY>
                        <angle>0</angle>
                        <opacity>1</opacity>
                    </world>
                </instance>
                <instance type="notepadNomes" uid="156">
                    <properties>
                        <character-width>16</character-width>
                        <character-height>16</character-height>
                        <character-set>ABCDEFGHIJKLMNOPQRSTUVWXYZabcdefghijklmnopqrstuvwxyz0123456789.,;:?!-_~#&quot;&apos;&amp;()[]|`\/@°+=*$£€&lt;&gt;</character-set>
                        <text>Karenf \n se</text>
                        <scale>1</scale>
                        <initial-visibility>Visible</initial-visibility>
                        <horizontal-alignment>Left</horizontal-alignment>
                        <vertical-alignment>Top</vertical-alignment>
                        <hotspot>Top-left</hotspot>
                        <wrapping>Word</wrapping>
                        <character-spacing>0</character-spacing>
                        <line-height>0</line-height>
                        <char-width-json></char-width-json>
                        <space-char-width>-1</space-char-width>
                    </properties>
                    <behavior-instances>
                        <behavior-instance type="Pin" />
                    </behavior-instances>
                    <blend-mode>0</blend-mode>
                    <effect-fallback>0</effect-fallback>
                    <world>
                        <x>-335</x>
                        <y>439</y>
                        <z>0</z>
                        <width>210</width>
                        <height>154</height>
                        <depth>0</depth>
                        <hotspotX>0</hotspotX>
                        <hotspotY>0</hotspotY>
                        <angle>0</angle>
                        <opacity>1</opacity>
                    </world>
                </instance>
            </instances>
            <effects />
        </layer>
    </layers>
    <nonworld-instances />
    <effects />
</c2layout>
